based_random
